README.rst
setup.py
msobox/__init__.py
msobox.egg-info/PKG-INFO
msobox.egg-info/SOURCES.txt
msobox.egg-info/dependency_links.txt
msobox.egg-info/requires.txt
msobox.egg-info/top_level.txt
msobox/ind/__init__.py
msobox/ind/base.py
msobox/ind/explicit_euler.py
msobox/ind/rk4classic.py
msobox/mf/__init__.py
msobox/mf/functions.py
msobox/mf/model.py