Metadata-Version: 1.1
Name: msobox
Version: 0.1.1
Summary: MSOBox - A Toolbox for Model-based Optimization
Home-page: https://bitbucket.org/msobox/msobox
Author: MSOBox Development Team
Author-email: msobox@hekori.com
License: BSD license
Keywords: numerical integration sensitivity generation
Platform: UNKNOWN
Classifier: Development Status :: 4 - Beta
Classifier: Intended Audience :: Education
Classifier: Intended Audience :: Science/Research
Classifier: License :: OSI Approved :: BSD License
Classifier: Programming Language :: Python :: 2.7
Classifier: Natural Language :: English
Classifier: Operating System :: POSIX :: Linux
Classifier: Topic :: Education
Classifier: Topic :: Education :: Testing
Classifier: Topic :: Scientific/Engineering
Classifier: Topic :: Scientific/Engineering :: Mathematics
Classifier: Topic :: Software Development :: Libraries
Classifier: Topic :: Software Development :: Libraries :: Application Frameworks
Classifier: Topic :: Software Development :: Libraries :: Python Modules
Classifier: Topic :: Utilities
